README.txt
setup.py
src/bobodoctestumentation/__init__.py
src/bobodoctestumentation/annotations.test
src/bobodoctestumentation/bobocalc.html
src/bobodoctestumentation/bobocalc.py
src/bobodoctestumentation/bobocalc.test
src/bobodoctestumentation/boboserver.test
src/bobodoctestumentation/conf.py
src/bobodoctestumentation/contents.txt
src/bobodoctestumentation/decorator.test
src/bobodoctestumentation/edit.html
src/bobodoctestumentation/examples.txt
src/bobodoctestumentation/fswiki.py
src/bobodoctestumentation/fswiki.test
src/bobodoctestumentation/fswikia.py
src/bobodoctestumentation/fswikia.test
src/bobodoctestumentation/index.txt
src/bobodoctestumentation/main.test
src/bobodoctestumentation/more.txt
src/bobodoctestumentation/reference.txt
src/bobodoctestumentation/static.py
src/bobodoctestumentation/static.test
src/bobodoctestumentation/tests.py
src/bobodoctestumentation.egg-info/PKG-INFO
src/bobodoctestumentation.egg-info/SOURCES.txt
src/bobodoctestumentation.egg-info/dependency_links.txt
src/bobodoctestumentation.egg-info/requires.txt
src/bobodoctestumentation.egg-info/top_level.txt