Metadata-Version: 1.0
Name: bobodoctestumentation
Version: 2.1.0
Summary: Bobo tests and documentation
Home-page: http://www.python.org/pypi/bobodoctestumentation
Author: Jim Fulton
Author-email: jim@zope.com
License: ZPL 2.1
Platform: UNKNOWN
